pylascontrol/__init__.py
pylascontrol/pylascontrol.py
pylascontrol-1.0.0.dist-info/licenses/LICENSE
pylascontrol-1.0.0.dist-info/METADATA
pylascontrol-1.0.0.dist-info/WHEEL
pylascontrol-1.0.0.dist-info/top_level.txt
pylascontrol-1.0.0.dist-info/RECORD
