Metadata-Version: 2.4
Name: pylascontrol
Version: 1.0.0
Summary: pylascontrol. Package for personal financial management. Beta version for educational use.
Home-page: https://github.com/rodrigoaraujorosa/pylascontrol
Author: Rodrigo de Araujo Rosa
Author-email: rodrigoaraujo.r@gmail.com
License: MIT
Classifier: Programming Language :: Python :: 3
Classifier: License :: OSI Approved :: MIT License
Classifier: Operating System :: OS Independent
Requires-Python: >=3.12
License-File: LICENSE
Dynamic: author
Dynamic: author-email
Dynamic: classifier
Dynamic: description
Dynamic: description-content-type
Dynamic: home-page
Dynamic: license
Dynamic: license-file
Dynamic: requires-python
Dynamic: summary
